LICENCE.txt
MANIFEST.in
PYPI.md
README.md
pyproject.toml
requirements-build.txt
requirements.txt
setup.py
dockreg/VERSION
dockreg/__init__.py
dockreg/docker.py
dockreg/exceptions.py
dockreg/version.py
dockreg.egg-info/PKG-INFO
dockreg.egg-info/SOURCES.txt
dockreg.egg-info/dependency_links.txt
dockreg.egg-info/entry_points.txt
dockreg.egg-info/requires.txt
dockreg.egg-info/top_level.txt
dockreg/cli/__init__.py
dockreg/cli/dockreg.py
dockreg/commands/__common__.py
dockreg/commands/__init__.py
dockreg/commands/copy_image_to_ecr.py
dockreg/commands/copy_image_to_registry.py
dockreg/commands/delete_images.py
dockreg/commands/delete_repo.py
dockreg/commands/garbage_collect.py
dockreg/commands/inspect_images.py
dockreg/commands/list_images.py
dockreg/commands/list_repos.py
dockreg/commands/registry_info.py
dockreg/commands/registry_restart.py
dockreg/commands/registry_start.py
dockreg/commands/registry_status.py
dockreg/commands/registry_stop.py
dockreg/lib/__init__.py
dockreg/lib/aws.py
dockreg/lib/misc.py